design.sv
module bidirectional_port (
    inout wire data_line,
    input wire direction,
    input wire data_out,
    output wire data_in
);

    assign data_line = direction ? data_out : 1'bz;
    assign data_in = data_line;

endmodule

testbench.sv
module tb_bidirectional_port;

    wire data_line;
    reg direction;
    reg data_out;
    wire data_in;
    
    reg external_data;
    reg external_drive;
    
    assign data_line = external_drive ? external_data : 1'bz;

    bidirectional_port dut (
        .data_line(data_line),
        .direction(direction),
        .data_out(data_out),
        .data_in(data_in)
    );

    initial begin
        $dumpfile("dump.vcd");
        $dumpvars(0, tb_bidirectional_port);
        
        direction = 0;
        data_out = 0;
        external_data = 0;
        external_drive = 0;
        
        $display("=== Bidirectional Port Testbench ===\n");
        
        $display("Test 1: OUTPUT MODE (direction=1)");
        direction = 1;
        external_drive = 0;
        
        data_out = 0;
        #10;
        $display("Time=%0t | Direction=%b | data_out=%b | data_line=%b | data_in=%b", 
                 $time, direction, data_out, data_line, data_in);
        
        data_out = 1;
        #10;
        $display("Time=%0t | Direction=%b | data_out=%b | data_line=%b | data_in=%b", 
                 $time, direction, data_out, data_line, data_in);
        
        $display("\nTest 2: INPUT MODE (direction=0)");
        direction = 0;
        external_drive = 1;
        
        external_data = 0;
        #10;
        $display("Time=%0t | Direction=%b | external_data=%b | data_line=%b | data_in=%b", 
                 $time, direction, external_data, data_line, data_in);
        
        external_data = 1;
        #10;
        $display("Time=%0t | Direction=%b | external_data=%b | data_line=%b | data_in=%b", 
                 $time, direction, external_data, data_line, data_in);
        
        $display("\nTest 3: TRANSITION (Output -> Input)");
        direction = 1;
        data_out = 1;
        external_drive = 0;
        #10;
        $display("Time=%0t | Mode=OUTPUT | data_line=%b", $time, data_line);
        
        direction = 0;
        #1;
        external_drive = 1;
        external_data = 0;
        #10;
        $display("Time=%0t | Mode=INPUT | data_line=%b (No contention)", $time, data_line);
        
        $display("\nTest 4: MULTIPLE TRANSITIONS");
        repeat(4) begin
            direction = 1;
            external_drive = 0;
            data_out = $random;
            #10;
            $display("Time=%0t | OUTPUT | data_out=%b -> data_line=%b", 
                     $time, data_out, data_line);
            
            direction = 0;
            #1;
            external_drive = 1;
            external_data = $random;
            #10;
            $display("Time=%0t | INPUT  | external_data=%b -> data_in=%b", 
                     $time, external_data, data_in);
        end
        
        $display("\n=== All Tests Completed ===");
        $finish;
    end
    
    always @(*) begin
        if (direction && external_drive) begin
            $display("WARNING: Bus contention at time %0t!", $time);
        end
    end

endmodule

dump.vcd
$date
	Sat Nov 15 01:56:42 2025
$end

$version
	Synopsys VCS version U-2023.03-SP2_Full64
$end

$timescale
	1ns
$end

$comment Csum: 1 bedc27dbcacc27f0 $end


$scope module tb_bidirectional_port $end
$var wire 1 ! data_line $end
$var reg 1 " direction $end
$var reg 1 # data_out $end
$var wire 1 ! data_in $end
$var reg 1 $ external_data $end
$var reg 1 % external_drive $end

$scope module dut $end
$var wire 1 ! data_line $end
$var wire 1 " direction $end
$var wire 1 # data_out $end
$var wire 1 ! data_in $end
$upscope $end

$upscope $end

$enddefinitions $end

#0
$dumpvars
0!
0#
1"
0$
0%
$end
#10
1#
1!
#20
0"
1%
0!
#30
1$
1!
#40
1"
0%
#50
0"
z!
#51
1%
0$
0!
#61
1"
0%
0#
#71
0"
z!
#72
1%
1$
1!
#82
1"
0%
1#
#92
0"
z!
#93
1%
1!
#103
1"
0%
#113
0"
z!
#114
1%
1!
#124
1"
0%
#134
0"
z!
#135
1%
0$
0!
